{
  "states": [
    {
      "state": "Andhra Pradesh",
      "districts": [
        "Anantapur North", "Anantapur South", "Anantapur East", "Anantapur West", "Anantapur Central",
        "Chittoor North", "Chittoor South", "Chittoor East", "Chittoor West", "Chittoor Central",
        "East Godavari North", "East Godavari South", "East Godavari East", "East Godavari West", "East Godavari Central",
        "Guntur North", "Guntur South", "Guntur East", "Guntur West", "Guntur Central",
        "Krishna North", "Krishna South", "Krishna East", "Krishna West", "Krishna Central",
        "Kurnool North", "Kurnool South", "Kurnool East", "Kurnool West", "Kurnool Central",
        "Nellore North", "Nellore South", "Nellore East", "Nellore West", "Nellore Central",
        "Prakasam North", "Prakasam South", "Prakasam East", "Prakasam West", "Prakasam Central",
        "Srikakulam North", "Srikakulam South", "Srikakulam East", "Srikakulam West", "Srikakulam Central",
        "Visakhapatnam North", "Visakhapatnam South", "Visakhapatnam East", "Visakhapatnam West", "Visakhapatnam Central",
        "Vizianagaram North", "Vizianagaram South", "Vizianagaram East", "Vizianagaram West", "Vizianagaram Central",
        "West Godavari North", "West Godavari South", "West Godavari East", "West Godavari West", "West Godavari Central",
        "Y.S.R. Kadapa North", "Y.S.R. Kadapa South", "Y.S.R. Kadapa East", "Y.S.R. Kadapa West", "Y.S.R. Kadapa Central"
      ]
    },
    {
      "state": "Arunachal Pradesh",
      "districts": [
        "Tawang North", "Tawang South", "Tawang East", "Tawang West", "Tawang Central",
        "West Kameng North", "West Kameng South", "West Kameng East", "West Kameng West", "West Kameng Central",
        "East Kameng North", "East Kameng South", "East Kameng East", "East Kameng West", "East Kameng Central",
        "Papum Pare North", "Papum Pare South", "Papum Pare East", "Papum Pare West", "Papum Pare Central",
        "Kurung Kumey North", "Kurung Kumey South", "Kurung Kumey East", "Kurung Kumey West", "Kurung Kumey Central",
        "Kra Daadi North", "Kra Daadi South", "Kra Daadi East", "Kra Daadi West", "Kra Daadi Central",
        "Lower Subansiri North", "Lower Subansiri South", "Lower Subansiri East", "Lower Subansiri West", "Lower Subansiri Central",
        "Upper Subansiri North", "Upper Subansiri South", "Upper Subansiri East", "Upper Subansiri West", "Upper Subansiri Central",
        "West Siang North", "West Siang South", "West Siang East", "West Siang West", "West Siang Central",
        "East Siang North", "East Siang South", "East Siang East", "East Siang West", "East Siang Central",
        "Siang North", "Siang South", "Siang East", "Siang West", "Siang Central",
        "Upper Siang North", "Upper Siang South", "Upper Siang East", "Upper Siang West", "Upper Siang Central",
        "Lower Siang North", "Lower Siang South", "Lower Siang East", "Lower Siang West", "Lower Siang Central",
        "Lower Dibang Valley North", "Lower Dibang Valley South", "Lower Dibang Valley East", "Lower Dibang Valley West", "Lower Dibang Valley Central",
        "Dibang Valley North", "Dibang Valley South", "Dibang Valley East", "Dibang Valley West", "Dibang Valley Central",
        "Anjaw North", "Anjaw South", "Anjaw East", "Anjaw West", "Anjaw Central",
        "Lohit North", "Lohit South", "Lohit East", "Lohit West", "Lohit Central",
        "Namsai North", "Namsai South", "Namsai East", "Namsai West", "Namsai Central",
        "Changlang North", "Changlang South", "Changlang East", "Changlang West", "Changlang Central",
        "Tirap North", "Tirap South", "Tirap East", "Tirap West", "Tirap Central",
        "Longding North", "Longding South", "Longding East", "Longding West", "Longding Central"
      ]
    },
    {
      "state": "Assam",
      "districts": [
        "Baksa North", "Baksa South", "Baksa East", "Baksa West", "Baksa Central",
        "Barpeta North", "Barpeta South", "Barpeta East", "Barpeta West", "Barpeta Central",
        "Biswanath North", "Biswanath South", "Biswanath East", "Biswanath West", "Biswanath Central",
        "Bongaigaon North", "Bongaigaon South", "Bongaigaon East", "Bongaigaon West", "Bongaigaon Central",
        "Cachar North", "Cachar South", "Cachar East", "Cachar West", "Cachar Central",
        "Charaideo North", "Charaideo South", "Charaideo East", "Charaideo West", "Charaideo Central",
        "Chirang North", "Chirang South", "Chirang East", "Chirang West", "Chirang Central",
        "Darrang North", "Darrang South", "Darrang East", "Darrang West", "Darrang Central",
        "Dhemaji North", "Dhemaji South", "Dhemaji East", "Dhemaji West", "Dhemaji Central",
        "Dhubri North", "Dhubri South", "Dhubri East", "Dhubri West", "Dhubri Central",
        "Dibrugarh North", "Dibrugarh South", "Dibrugarh East", "Dibrugarh West", "Dibrugarh Central",
        "Dima Hasao North", "Dima Hasao South", "Dima Hasao East", "Dima Hasao West", "Dima Hasao Central",
        "Goalpara North", "Goalpara South", "Goalpara East", "Goalpara West", "Goalpara Central",
        "Golaghat North", "Golaghat South", "Golaghat East", "Golaghat West", "Golaghat Central",
        "Hailakandi North", "Hailakandi South", "Hailakandi East", "Hailakandi West", "Hailakandi Central",
        "Hojai North", "Hojai South", "Hojai East", "Hojai West", "Hojai Central",
        "Jorhat North", "Jorhat South", "Jorhat East", "Jorhat West", "Jorhat Central",
        "Kamrup Metropolitan North", "Kamrup Metropolitan South", "Kamrup Metropolitan East", "Kamrup Metropolitan West", "Kamrup Metropolitan Central",
        "Kamrup North", "Kamrup South", "Kamrup East", "Kamrup West", "Kamrup Central",
        "Karbi Anglong North", "Karbi Anglong South", "Karbi Anglong East", "Karbi Anglong West", "Karbi Anglong Central",
        "Karimganj North", "Karimganj South", "Karimganj East", "Karimganj West", "Karimganj Central",
        "Kokrajhar North", "Kokrajhar South", "Kokrajhar East", "Kokrajhar West", "Kokrajhar Central",
        "Lakhimpur North", "Lakhimpur South", "Lakhimpur East", "Lakhimpur West", "Lakhimpur Central",
        "Majuli North", "Majuli South", "Majuli East", "Majuli West", "Majuli Central",
        "Morigaon North", "Morigaon South", "Morigaon East", "Morigaon West", "Morigaon Central",
        "Nagaon North", "Nagaon South", "Nagaon East", "Nagaon West", "Nagaon Central",
        "Nalbari North", "Nalbari South", "Nalbari East", "Nalbari West", "Nalbari Central",
        "Sivasagar North", "Sivasagar South", "Sivasagar East", "Sivasagar West", "Sivasagar Central",
        "Sonitpur North", "Sonitpur South", "Sonitpur East", "Sonitpur West", "Sonitpur Central",
        "South Salmara-Mankachar North", "South Salmara-Mankachar South", "South Salmara-Mankachar East", "South Salmara-Mankachar West", "South Salmara-Mankachar Central",
        "Tinsukia North", "Tinsukia South", "Tinsukia East", "Tinsukia West", "Tinsukia Central",
        "Udalguri North", "Udalguri South", "Udalguri East", "Udalguri West", "Udalguri Central",
        "West Karbi Anglong North", "West Karbi Anglong South", "West Karbi Anglong East", "West Karbi Anglong West", "West Karbi Anglong Central"
      ]
    },
    {
      "state": "Bihar",
      "districts": [
        "Araria North", "Araria South", "Araria East", "Araria West", "Araria Central",
        "Arwal North", "Arwal South", "Arwal East", "Arwal West", "Arwal Central",
        "Aurangabad North", "Aurangabad South", "Aurangabad East", "Aurangabad West", "Aurangabad Central",
        "Banka North", "Banka South", "Banka East", "Banka West", "Banka Central",
        "Begusarai North", "Begusarai South", "Begusarai East", "Begusarai West", "Begusarai Central",
        "Bhagalpur North", "Bhagalpur South", "Bhagalpur East", "Bhagalpur West", "Bhagalpur Central",
        "Bhojpur North", "Bhojpur South", "Bhojpur East", "Bhojpur West", "Bhojpur Central",
        "Buxar North", "Buxar South", "Buxar East", "Buxar West", "Buxar Central",
        "Darbhanga North", "Darbhanga South", "Darbhanga East", "Darbhanga West", "Darbhanga Central",
        "East Champaran North", "East Champaran South", "East Champaran East", "East Champaran West", "East Champaran Central",
        "Gaya North", "Gaya South", "Gaya East", "Gaya West", "Gaya Central",
        "Gopalganj North", "Gopalganj South", "Gopalganj East", "Gopalganj West", "Gopalganj Central",
        "Jamui North", "Jamui South", "Jamui East", "Jamui West", "Jamui Central",
        "Jehanabad North", "Jehanabad South", "Jehanabad East", "Jehanabad West", "Jehanabad Central",
        "Kaimur North", "Kaimur South", "Kaimur East", "Kaimur West", "Kaimur Central",
        "Katihar North", "Katihar South", "Katihar East", "Katihar West", "Katihar Central",
        "Khagaria North", "Khagaria South", "Khagaria East", "Khagaria West", "Khagaria Central",
        "Kishanganj North", "Kishanganj South", "Kishanganj East", "Kishanganj West", "Kishanganj Central",
        "Lakhisarai North", "Lakhisarai South", "Lakhisarai East", "Lakhisarai West", "Lakhisarai Central",
        "Madhepura North", "Madhepura South", "Madhepura East", "Madhepura West", "Madhepura Central",
        "Madhubani North", "Madhubani South", "Madhubani East", "Madhubani West", "Madhubani Central",
        "Munger North", "Munger South", "Munger East", "Munger West", "Munger Central",
        "Muzaffarpur North", "Muzaffarpur South", "Muzaffarpur East", "Muzaffarpur West", "Muzaffarpur Central",
        "Nalanda North", "Nalanda South", "Nalanda East", "Nalanda West", "Nalanda Central",
        "Nawada North", "Nawada South", "Nawada East", "Nawada West", "Nawada Central",
        "Patna North", "Patna South", "Patna East", "Patna West", "Patna Central",
        "Purnia North", "Purnia South", "Purnia East", "Purnia West", "Purnia Central",
        "Rohtas North", "Rohtas South", "Rohtas East", "Rohtas West", "Rohtas Central",
        "Saharsa North", "Saharsa South", "Saharsa East", "Saharsa West", "Saharsa Central",
        "Samastipur North", "Samastipur South", "Samastipur East", "Samastipur West", "Samastipur Central",
        "Saran North", "Saran South", "Saran East", "Saran West", "Saran Central",
        "Sheikhpura North", "Sheikhpura South", "Sheikhpura East", "Sheikhpura West", "Sheikhpura Central",
        "Sheohar North", "Sheohar South", "Sheohar East", "Sheohar West", "Sheohar Central",
        "Sitamarhi North", "Sitamarhi South", "Sitamarhi East", "Sitamarhi West", "Sitamarhi Central",
        "Siwan North", "Siwan South", "Siwan East", "Siwan West", "Siwan Central",
        "Supaul North", "Supaul South", "Supaul East", "Supaul West", "Supaul Central",
        "Vaishali North", "Vaishali South", "Vaishali East", "Vaishali West", "Vaishali Central",
        "West Champaran North", "West Champaran South", "West Champaran East", "West Champaran West", "West Champaran Central"
      ]
    },
    {
      "state": "Chhattisgarh",
      "districts": [
        "Balod North", "Balod South", "Balod East", "Balod West", "Balod Central",
        "Baloda Bazar North", "Baloda Bazar South", "Baloda Bazar East", "Baloda Bazar West", "Baloda Bazar Central",
        "Balrampur North", "Balrampur South", "Balrampur East", "Balrampur West", "Balrampur Central",
        "Bastar North", "Bastar South", "Bastar East", "Bastar West", "Bastar Central",
        "Bemetara North", "Bemetara South", "Bemetara East", "Bemetara West", "Bemetara Central",
        "Bijapur North", "Bijapur South", "Bijapur East", "Bijapur West", "Bijapur Central",
        "Bilaspur North", "Bilaspur South", "Bilaspur East", "Bilaspur West", "Bilaspur Central",
        "Dantewada North", "Dantewada South", "Dantewada East", "Dantewada West", "Dantewada Central",
        "Dhamtari North", "Dhamtari South", "Dhamtari East", "Dhamtari West", "Dhamtari Central",
        "Durg North", "Durg South", "Durg East", "Durg West", "Durg Central",
        "Gariaband North", "Gariaband South", "Gariaband East", "Gariaband West", "Gariaband Central",
        "Janjgir-Champa North", "Janjgir-Champa South", "Janjgir-Champa East", "Janjgir-Champa West", "Janjgir-Champa Central",
        "Jashpur North", "Jashpur South", "Jashpur East", "Jashpur West", "Jashpur Central",
        "Kabirdham North", "Kabirdham South", "Kabirdham East", "Kabirdham West", "Kabirdham Central",
        "Kanker North", "Kanker South", "Kanker East", "Kanker West", "Kanker Central",
        "Kondagaon North", "Kondagaon South", "Kondagaon East", "Kondagaon West", "Kondagaon Central",
        "Korba North", "Korba South", "Korba East", "Korba West", "Korba Central",
        "Koriya North", "Koriya South", "Koriya East", "Koriya West", "Koriya Central",
        "Mahasamund North", "Mahasamund South", "Mahasamund East", "Mahasamund West", "Mahasamund Central",
        "Mungeli North", "Mungeli South", "Mungeli East", "Mungeli West", "Mungeli Central",
        "Narayanpur North", "Narayanpur South", "Narayanpur East", "Narayanpur West", "Narayanpur Central",
        "Raigarh North", "Raigarh South", "Raigarh East", "Raigarh West", "Raigarh Central",
        "Raipur North", "Raipur South", "Raipur East", "Raipur West", "Raipur Central",
        "Rajnandgaon North", "Rajnandgaon South", "Rajnandgaon East", "Rajnandgaon West", "Rajnandgaon Central",
        "Sukma North", "Sukma South", "Sukma East", "Sukma West", "Sukma Central",
        "Surajpur North", "Surajpur South", "Surajpur East", "Surajpur West", "Surajpur Central",
        "Surguja North", "Surguja South", "Surguja East", "Surguja West", "Surguja Central"
      ]
    },
    {
      "state": "Goa",
      "districts": [
        "North Goa North", "North Goa South", "North Goa East", "North Goa West", "North Goa Central",
        "South Goa North", "South Goa South", "South Goa East", "South Goa West", "South Goa Central"
      ]
    },
    {
      "state": "Gujarat",
      "districts": [
        "Ahmedabad North", "Ahmedabad South", "Ahmedabad East", "Ahmedabad West", "Ahmedabad Central",
        "Amreli North", "Amreli South", "Amreli East", "Amreli West", "Amreli Central",
        "Anand North", "Anand South", "Anand East", "Anand West", "Anand Central",
        "Aravalli North", "Aravalli South", "Aravalli East", "Aravalli West", "Aravalli Central",
        "Banaskantha North", "Banaskantha South", "Banaskantha East", "Banaskantha West", "Banaskantha Central",
        "Bharuch North", "Bharuch South", "Bharuch East", "Bharuch West", "Bharuch Central",
        "Bhavnagar North", "Bhavnagar South", "Bhavnagar East", "Bhavnagar West", "Bhavnagar Central",
        "Botad North", "Botad South", "Botad East", "Botad West", "Botad Central",
        "Chhota Udaipur North", "Chhota Udaipur South", "Chhota Udaipur East", "Chhota Udaipur West", "Chhota Udaipur Central",
        "Dahod North", "Dahod South", "Dahod East", "Dahod West", "Dahod Central",
        "Dang North", "Dang South", "Dang East", "Dang West", "Dang Central",
        "Devbhoomi Dwarka North", "Devbhoomi Dwarka South", "Devbhoomi Dwarka East", "Devbhoomi Dwarka West", "Devbhoomi Dwarka Central",
        "Gandhinagar North", "Gandhinagar South", "Gandhinagar East", "Gandhinagar West", "Gandhinagar Central",
        "Gir Somnath North", "Gir Somnath South", "Gir Somnath East", "Gir Somnath West", "Gir Somnath Central",
        "Jamnagar North", "Jamnagar South", "Jamnagar East", "Jamnagar West", "Jamnagar Central",
        "Junagadh North", "Junagadh South", "Junagadh East", "Junagadh West", "Junagadh Central",
        "Kheda North", "Kheda South", "Kheda East", "Kheda West", "Kheda Central",
        "Kutch North", "Kutch South", "Kutch East", "Kutch West", "Kutch Central",
        "Mahisagar North", "Mahisagar South", "Mahisagar East", "Mahisagar West", "Mahisagar Central",
        "Mehsana North", "Mehsana South", "Mehsana East", "Mehsana West", "Mehsana Central",
        "Morbi North", "Morbi South", "Morbi East", "Morbi West", "Morbi Central",
        "Narmada North", "Narmada South", "Narmada East", "Narmada West", "Narmada Central",
        "Navsari North", "Navsari South", "Navsari East", "Navsari West", "Navsari Central",
        "Panchmahal North", "Panchmahal South", "Panchmahal East", "Panchmahal West", "Panchmahal Central",
        "Patan North", "Patan South", "Patan East", "Patan West", "Patan Central",
        "Porbandar North", "Porbandar South", "Porbandar East", "Porbandar West", "Porbandar Central",
        "Rajkot North", "Rajkot South", "Rajkot East", "Rajkot West", "Rajkot Central",
        "Sabarkantha North", "Sabarkantha South", "Sabarkantha East", "Sabarkantha West", "Sabarkantha Central",
        "Surat North", "Surat South", "Surat East", "Surat West", "Surat Central",
        "Surendranagar North", "Surendranagar South", "Surendranagar East", "Surendranagar West", "Surendranagar Central",
        "Tapi North", "Tapi South", "Tapi East", "Tapi West", "Tapi Central",
        "Vadodara North", "Vadodara South", "Vadodara East", "Vadodara West", "Vadodara Central",
        "Valsad North", "Valsad South", "Valsad East", "Valsad West", "Valsad Central"
      ]
    },
    {
      "state": "Haryana",
      "districts": [
        "Ambala North", "Ambala South", "Ambala East", "Ambala West", "Ambala Central",
        "Bhiwani North", "Bhiwani South", "Bhiwani East", "Bhiwani West", "Bhiwani Central",
        "Charkhi Dadri North", "Charkhi Dadri South", "Charkhi Dadri East", "Charkhi Dadri West", "Charkhi Dadri Central",
        "Faridabad North", "Faridabad South", "Faridabad East", "Faridabad West", "Faridabad Central",
        "Fatehabad North", "Fatehabad South", "Fatehabad East", "Fatehabad West", "Fatehabad Central",
        "Gurugram North", "Gurugram South", "Gurugram East", "Gurugram West", "Gurugram Central",
        "Hisar North", "Hisar South", "Hisar East", "Hisar West", "Hisar Central",
        "Jhajjar North", "Jhajjar South", "Jhajjar East", "Jhajjar West", "Jhajjar Central",
        "Jind North", "Jind South", "Jind East", "Jind West", "Jind Central",
        "Kaithal North", "Kaithal South", "Kaithal East", "Kaithal West", "Kaithal Central",
        "Karnal North", "Karnal South", "Karnal East", "Karnal West", "Karnal Central",
        "Kurukshetra North", "Kurukshetra South", "Kurukshetra East", "Kurukshetra West", "Kurukshetra Central",
        "Mahendragarh North", "Mahendragarh South", "Mahendragarh East", "Mahendragarh West", "Mahendragarh Central",
        "Nuh North", "Nuh South", "Nuh East", "Nuh West", "Nuh Central",
        "Palwal North", "Palwal South", "Palwal East", "Palwal West", "Palwal Central",
        "Panchkula North", "Panchkula South", "Panchkula East", "Panchkula West", "Panchkula Central",
        "Panipat North", "Panipat South", "Panipat East", "Panipat West", "Panipat Central",
        "Rewari North", "Rewari South", "Rewari East", "Rewari West", "Rewari Central",
        "Rohtak North", "Rohtak South", "Rohtak East", "Rohtak West", "Rohtak Central",
        "Sirsa North", "Sirsa South", "Sirsa East", "Sirsa West", "Sirsa Central",
        "Sonipat North", "Sonipat South", "Sonipat East", "Sonipat West", "Sonipat Central",
        "Yamunanagar North", "Yamunanagar South", "Yamunanagar East", "Yamunanagar West", "Yamunanagar Central"
      ]
    },
    {
      "state": "Himachal Pradesh",
      "districts": [
        "Bilaspur North", "Bilaspur South", "Bilaspur East", "Bilaspur West", "Bilaspur Central",
        "Chamba North", "Chamba South", "Chamba East", "Chamba West", "Chamba Central",
        "Hamirpur North", "Hamirpur South", "Hamirpur East", "Hamirpur West", "Hamirpur Central",
        "Kangra North", "Kangra South", "Kangra East", "Kangra West", "Kangra Central",
        "Kinnaur North", "Kinnaur South", "Kinnaur East", "Kinnaur West", "Kinnaur Central",
        "Kullu North", "Kullu South", "Kullu East", "Kullu West", "Kullu Central",
        "Lahaul and Spiti North", "Lahaul and Spiti South", "Lahaul and Spiti East", "Lahaul and Spiti West", "Lahaul and Spiti Central",
        "Mandi North", "Mandi South", "Mandi East", "Mandi West", "Mandi Central",
        "Shimla North", "Shimla South", "Shimla East", "Shimla West", "Shimla Central",
        "Sirmaur North", "Sirmaur South", "Sirmaur East", "Sirmaur West", "Sirmaur Central",
        "Solan North", "Solan South", "Solan East", "Solan West", "Solan Central",
        "Una North", "Una South", "Una East", "Una West", "Una Central"
      ]
    },
    {
      "state": "Jharkhand",
      "districts": [
        "Bokaro North", "Bokaro South", "Bokaro East", "Bokaro West", "Bokaro Central",
        "Chatra North", "Chatra South", "Chatra East", "Chatra West", "Chatra Central",
        "Deoghar North", "Deoghar South", "Deoghar East", "Deoghar West", "Deoghar Central",
        "Dhanbad North", "Dhanbad South", "Dhanbad East", "Dhanbad West", "Dhanbad Central",
        "Dumka North", "Dumka South", "Dumka East", "Dumka West", "Dumka Central",
        "East Singhbhum North", "East Singhbhum South", "East Singhbhum East", "East Singhbhum West", "East Singhbhum Central",
        "Garhwa North", "Garhwa South", "Garhwa East", "Garhwa West", "Garhwa Central",
        "Giridih North", "Giridih South", "Giridih East", "Giridih West", "Giridih Central",
        "Godda North", "Godda South", "Godda East", "Godda West", "Godda Central",
        "Gumla North", "Gumla South", "Gumla East", "Gumla West", "Gumla Central",
        "Hazaribagh North", "Hazaribagh South", "Hazaribagh East", "Hazaribagh West", "Hazaribagh Central",
        "Jamtara North", "Jamtara South", "Jamtara East", "Jamtara West", "Jamtara Central",
        "Khunti North", "Khunti South", "Khunti East", "Khunti West", "Khunti Central",
        "Koderma North", "Koderma South", "Koderma East", "Koderma West", "Koderma Central",
        "Latehar North", "Latehar South", "Latehar East", "Latehar West", "Latehar Central",
        "Lohardaga North", "Lohardaga South", "Lohardaga East", "Lohardaga West", "Lohardaga Central",
        "Pakur North", "Pakur South", "Pakur East", "Pakur West", "Pakur Central",
        "Palamu North", "Palamu South", "Palamu East", "Palamu West", "Palamu Central",
        "Ramgarh North", "Ramgarh South", "Ramgarh East", "Ramgarh West", "Ramgarh Central",
        "Ranchi North", "Ranchi South", "Ranchi East", "Ranchi West", "Ranchi Central",
        "Sahebganj North", "Sahebganj South", "Sahebganj East", "Sahebganj West", "Sahebganj Central",
        "Seraikela Kharsawan North", "Seraikela Kharsawan South", "Seraikela Kharsawan East", "Seraikela Kharsawan West", "Seraikela Kharsawan Central",
        "Simdega North", "Simdega South", "Simdega East", "Simdega West", "Simdega Central",
        "West Singhbhum North", "West Singhbhum South", "West Singhbhum East", "West Singhbhum West", "West Singhbhum Central"
      ]
    },
    {
      "state": "Karnataka",
      "districts": [
        "Bagalkot North", "Bagalkot South", "Bagalkot East", "Bagalkot West", "Bagalkot Central",
        "Ballari North", "Ballari South", "Ballari East", "Ballari West", "Ballari Central",
        "Belagavi North", "Belagavi South", "Belagavi East", "Belagavi West", "Belagavi Central",
        "Bengaluru Rural North", "Bengaluru Rural South", "Bengaluru Rural East", "Bengaluru Rural West", "Bengaluru Rural Central",
        "Bengaluru Urban North", "Bengaluru Urban South", "Bengaluru Urban East", "Bengaluru Urban West", "Bengaluru Urban Central",
        "Bidar North", "Bidar South", "Bidar East", "Bidar West", "Bidar Central",
        "Chamarajanagar North", "Chamarajanagar South", "Chamarajanagar East", "Chamarajanagar West", "Chamarajanagar Central",
        "Chikballapur North", "Chikballapur South", "Chikballapur East", "Chikballapur West", "Chikballapur Central",
        "Chikkamagaluru North", "Chikkamagaluru South", "Chikkamagaluru East", "Chikkamagaluru West", "Chikkamagaluru Central",
        "Chitradurga North", "Chitradurga South", "Chitradurga East", "Chitradurga West", "Chitradurga Central",
        "Dakshina Kannada North", "Dakshina Kannada South", "Dakshina Kannada East", "Dakshina Kannada West", "Dakshina Kannada Central",
        "Davanagere North", "Davanagere South", "Davanagere East", "Davanagere West", "Davanagere Central",
        "Dharwad North", "Dharwad South", "Dharwad East", "Dharwad West", "Dharwad Central",
        "Gadag North", "Gadag South", "Gadag East", "Gadag West", "Gadag Central",
        "Hassan North", "Hassan South", "Hassan East", "Hassan West", "Hassan Central",
        "Haveri North", "Haveri South", "Haveri East", "Haveri West", "Haveri Central",
        "Kalaburagi North", "Kalaburagi South", "Kalaburagi East", "Kalaburagi West", "Kalaburagi Central",
        "Kodagu North", "Kodagu South", "Kodagu East", "Kodagu West", "Kodagu Central",
        "Kolar North", "Kolar South", "Kolar East", "Kolar West", "Kolar Central",
        "Koppal North", "Koppal South", "Koppal East", "Koppal West", "Koppal Central",
        "Mandya North", "Mandya South", "Mandya East", "Mandya West", "Mandya Central",
        "Mysuru North", "Mysuru South", "Mysuru East", "Mysuru West", "Mysuru Central",
        "Raichur North", "Raichur South", "Raichur East", "Raichur West", "Raichur Central",
        "Ramanagara North", "Ramanagara South", "Ramanagara East", "Ramanagara West", "Ramanagara Central",
        "Shivamogga North", "Shivamogga South", "Shivamogga East", "Shivamogga West", "Shivamogga Central",
        "Tumakuru North", "Tumakuru South", "Tumakuru East", "Tumakuru West", "Tumakuru Central",
        "Udupi North", "Udupi South", "Udupi East", "Udupi West", "Udupi Central",
        "Uttara Kannada North", "Uttara Kannada South", "Uttara Kannada East", "Uttara Kannada West", "Uttara Kannada Central",
        "Vijayapura North", "Vijayapura South", "Vijayapura East", "Vijayapura West", "Vijayapura Central",
        "Yadgir North", "Yadgir South", "Yadgir East", "Yadgir West", "Yadgir Central"
      ]
    },
    {
      "state": "Kerala",
      "districts": [
        "Alappuzha North", "Alappuzha South", "Alappuzha East", "Alappuzha West", "Alappuzha Central",
        "Ernakulam North", "Ernakulam South", "Ernakulam East", "Ernakulam West", "Ernakulam Central",
        "Idukki North", "Idukki South", "Idukki East", "Idukki West", "Idukki Central",
        "Kannur North", "Kannur South", "Kannur East", "Kannur West", "Kannur Central",
        "Kasaragod North", "Kasaragod South", "Kasaragod East", "Kasaragod West", "Kasaragod Central",
        "Kollam North", "Kollam South", "Kollam East", "Kollam West", "Kollam Central",
        "Kottayam North", "Kottayam South", "Kottayam East", "Kottayam West", "Kottayam Central",
        "Kozhikode North", "Kozhikode South", "Kozhikode East", "Kozhikode West", "Kozhikode Central",
        "Malappuram North", "Malappuram South", "Malappuram East", "Malappuram West", "Malappuram Central",
        "Palakkad North", "Palakkad South", "Palakkad East", "Palakkad West", "Palakkad Central",
        "Pathanamthitta North", "Pathanamthitta South", "Pathanamthitta East", "Pathanamthitta West", "Pathanamthitta Central",
        "Thiruvananthapuram North", "Thiruvananthapuram South", "Thiruvananthapuram East", "Thiruvananthapuram West", "Thiruvananthapuram Central",
        "Thrissur North", "Thrissur South", "Thrissur East", "Thrissur West", "Thrissur Central",
        "Wayanad North", "Wayanad South", "Wayanad East", "Wayanad West", "Wayanad Central"
      ]
    },
    {
      "state": "Madhya Pradesh",
      "districts": [
        "Agar Malwa North", "Agar Malwa South", "Agar Malwa East", "Agar Malwa West", "Agar Malwa Central",
        "Alirajpur North", "Alirajpur South", "Alirajpur East", "Alirajpur West", "Alirajpur Central",
        "Anuppur North", "Anuppur South", "Anuppur East", "Anuppur West", "Anuppur Central",
        "Ashoknagar North", "Ashoknagar South", "Ashoknagar East", "Ashoknagar West", "Ashoknagar Central",
        "Balaghat North", "Balaghat South", "Balaghat East", "Balaghat West", "Balaghat Central",
        "Barwani North", "Barwani South", "Barwani East", "Barwani West", "Barwani Central",
        "Betul North", "Betul South", "Betul East", "Betul West", "Betul Central",
        "Bhind North", "Bhind South", "Bhind East", "Bhind West", "Bhind Central",
        "Bhopal North", "Bhopal South", "Bhopal East", "Bhopal West", "Bhopal Central",
        "Burhanpur North", "Burhanpur South", "Burhanpur East", "Burhanpur West", "Burhanpur Central",
        "Chhatarpur North", "Chhatarpur South", "Chhatarpur East", "Chhatarpur West", "Chhatarpur Central",
        "Chhindwara North", "Chhindwara South", "Chhindwara East", "Chhindwara West", "Chhindwara Central",
        "Damoh North", "Damoh South", "Damoh East", "Damoh West", "Damoh Central",
        "Datia North", "Datia South", "Datia East", "Datia West", "Datia Central",
        "Dewas North", "Dewas South", "Dewas East", "Dewas West", "Dewas Central",
        "Dhar North", "Dhar South", "Dhar East", "Dhar West", "Dhar Central",
        "Dindori North", "Dindori South", "Dindori East", "Dindori West", "Dindori Central",
        "Guna North", "Guna South", "Guna East", "Guna West", "Guna Central",
        "Gwalior North", "Gwalior South", "Gwalior East", "Gwalior West", "Gwalior Central",
        "Harda North", "Harda South", "Harda East", "Harda West", "Harda Central",
        "Hoshangabad North", "Hoshangabad South", "Hoshangabad East", "Hoshangabad West", "Hoshangabad Central",
        "Indore North", "Indore South", "Indore East", "Indore West", "Indore Central",
        "Jabalpur North", "Jabalpur South", "Jabalpur East", "Jabalpur West", "Jabalpur Central",
        "Jhabua North", "Jhabua South", "Jhabua East", "Jhabua West", "Jhabua Central",
        "Katni North", "Katni South", "Katni East", "Katni West", "Katni Central",
        "Khandwa North", "Khandwa South", "Khandwa East", "Khandwa West", "Khandwa Central",
        "Khargone North", "Khargone South", "Khargone East", "Khargone West", "Khargone Central",
        "Mandla North", "Mandla South", "Mandla East", "Mandla West", "Mandla Central",
        "Mandsaur North", "Mandsaur South", "Mandsaur East", "Mandsaur West", "Mandsaur Central",
        "Morena North", "Morena South", "Morena East", "Morena West", "Morena Central",
        "Narsinghpur North", "Narsinghpur South", "Narsinghpur East", "Narsinghpur West", "Narsinghpur Central",
        "Neemuch North", "Neemuch South", "Neemuch East", "Neemuch West", "Neemuch Central",
        "Panna North", "Panna South", "Panna East", "Panna West", "Panna Central",
        "Raisen North", "Raisen South", "Raisen East", "Raisen West", "Raisen Central",
        "Rajgarh North", "Rajgarh South", "Rajgarh East", "Rajgarh West", "Rajgarh Central",
        "Ratlam North", "Ratlam South", "Ratlam East", "Ratlam West", "Ratlam Central",
        "Rewa North", "Rewa South", "Rewa East", "Rewa West", "Rewa Central",
        "Sagar North", "Sagar South", "Sagar East", "Sagar West", "Sagar Central",
        "Satna North", "Satna South", "Satna East", "Satna West", "Satna Central",
        "Sehore North", "Sehore South", "Sehore East", "Sehore West", "Sehore Central",
        "Seoni North", "Seoni South", "Seoni East", "Seoni West", "Seoni Central",
        "Shahdol North", "Shahdol South", "Shahdol East", "Shahdol West", "Shahdol Central",
        "Shajapur North", "Shajapur South", "Shajapur East", "Shajapur West", "Shajapur Central",
        "Sheopur North", "Sheopur South", "Sheopur East", "Sheopur West", "Sheopur Central",
        "Shivpuri North", "Shivpuri South", "Shivpuri East", "Shivpuri West", "Shivpuri Central",
        "Sidhi North", "Sidhi South", "Sidhi East", "Sidhi West", "Sidhi Central",
        "Singrauli North", "Singrauli South", "Singrauli East", "Singrauli West", "Singrauli Central",
        "Tikamgarh North", "Tikamgarh South", "Tikamgarh East", "Tikamgarh West", "Tikamgarh Central",
        "Ujjain North", "Ujjain South", "Ujjain East", "Ujjain West", "Ujjain Central",
        "Umaria North", "Umaria South", "Umaria East", "Umaria West", "Umaria Central",
        "Vidisha North", "Vidisha South", "Vidisha East", "Vidisha West", "Vidisha Central"
      ]
    },
    {
      "state": "Maharashtra",
      "districts": [
        "Ahmednagar North", "Ahmednagar South", "Ahmednagar East", "Ahmednagar West", "Ahmednagar Central",
        "Akola North", "Akola South", "Akola East", "Akola West", "Akola Central",
        "Amravati North", "Amravati South", "Amravati East", "Amravati West", "Amravati Central",
        "Aurangabad North", "Aurangabad South", "Aurangabad East", "Aurangabad West", "Aurangabad Central",
        "Beed North", "Beed South", "Beed East", "Beed West", "Beed Central",
        "Bhandara North", "Bhandara South", "Bhandara East", "Bhandara West", "Bhandara Central",
        "Buldhana North", "Buldhana South", "Buldhana East", "Buldhana West", "Buldhana Central",
        "Chandrapur North", "Chandrapur South", "Chandrapur East", "Chandrapur West", "Chandrapur Central",
        "Dhule North", "Dhule South", "Dhule East", "Dhule West", "Dhule Central",
        "Gadchiroli North", "Gadchiroli South", "Gadchiroli East", "Gadchiroli West", "Gadchiroli Central",
        "Gondia North", "Gondia South", "Gondia East", "Gondia West", "Gondia Central",
        "Hingoli North", "Hingoli South", "Hingoli East", "Hingoli West", "Hingoli Central",
        "Jalgaon North", "Jalgaon South", "Jalgaon East", "Jalgaon West", "Jalgaon Central",
        "Jalna North", "Jalna South", "Jalna East", "Jalna West", "Jalna Central",
        "Kolhapur North", "Kolhapur South", "Kolhapur East", "Kolhapur West", "Kolhapur Central",
        "Latur North", "Latur South", "Latur East", "Latur West", "Latur Central",
        "Mumbai City North", "Mumbai City South", "Mumbai City East", "Mumbai City West", "Mumbai City Central",
        "Mumbai Suburban North", "Mumbai Suburban South", "Mumbai Suburban East", "Mumbai Suburban West", "Mumbai Suburban Central",
        "Nagpur North", "Nagpur South", "Nagpur East", "Nagpur West", "Nagpur Central",
        "Nanded North", "Nanded South", "Nanded East", "Nanded West", "Nanded Central",
        "Nandurbar North", "Nandurbar South", "Nandurbar East", "Nandurbar West", "Nandurbar Central",
        "Nashik North", "Nashik South", "Nashik East", "Nashik West", "Nashik Central",
        "Osmanabad North", "Osmanabad South", "Osmanabad East", "Osmanabad West", "Osmanabad Central",
        "Palghar North", "Palghar South", "Palghar East", "Palghar West", "Palghar Central",
        "Parbhani North", "Parbhani South", "Parbhani East", "Parbhani West", "Parbhani Central",
        "Pune North", "Pune South", "Pune East", "Pune West", "Pune Central",
        "Raigad North", "Raigad South", "Raigad East", "Raigad West", "Raigad Central",
        "Ratnagiri North", "Ratnagiri South", "Ratnagiri East", "Ratnagiri West", "Ratnagiri Central",
        "Sangli North", "Sangli South", "Sangli East", "Sangli West", "Sangli Central",
        "Satara North", "Satara South", "Satara East", "Satara West", "Satara Central",
        "Sindhudurg North", "Sindhudurg South", "Sindhudurg East", "Sindhudurg West", "Sindhudurg Central",
        "Solapur North", "Solapur South", "Solapur East", "Solapur West", "Solapur Central",
        "Thane North", "Thane South", "Thane East", "Thane West", "Thane Central",
        "Wardha North", "Wardha South", "Wardha East", "Wardha West", "Wardha Central",
        "Washim North", "Washim South", "Washim East", "Washim West", "Washim Central",
        "Yavatmal North", "Yavatmal South", "Yavatmal East", "Yavatmal West", "Yavatmal Central"
      ]
    },
    {
      "state": "Manipur",
      "districts": [
        "Bishnupur North", "Bishnupur South", "Bishnupur East", "Bishnupur West", "Bishnupur Central",
        "Chandel North", "Chandel South", "Chandel East", "Chandel West", "Chandel Central",
        "Churachandpur North", "Churachandpur South", "Churachandpur East", "Churachandpur West", "Churachandpur Central",
        "Imphal East North", "Imphal East South", "Imphal East East", "Imphal East West", "Imphal East Central",
        "Imphal West North", "Imphal West South", "Imphal West East", "Imphal West West", "Imphal West Central",
        "Jiribam North", "Jiribam South", "Jiribam East", "Jiribam West", "Jiribam Central",
        "Kakching North", "Kakching South", "Kakching East", "Kakching West", "Kakching Central",
        "Kamjong North", "Kamjong South", "Kamjong East", "Kamjong West", "Kamjong Central",
        "Kangpokpi North", "Kangpokpi South", "Kangpokpi East", "Kangpokpi West", "Kangpokpi Central",
        "Noney North", "Noney South", "Noney East", "Noney West", "Noney Central",
        "Pherzawl North", "Pherzawl South", "Pherzawl East", "Pherzawl West", "Pherzawl Central",
        "Senapati North", "Senapati South", "Senapati East", "Senapati West", "Senapati Central",
        "Tamenglong North", "Tamenglong South", "Tamenglong East", "Tamenglong West", "Tamenglong Central",
        "Tengnoupal North", "Tengnoupal South", "Tengnoupal East", "Tengnoupal West", "Tengnoupal Central",
        "Thoubal North", "Thoubal South", "Thoubal East", "Thoubal West", "Thoubal Central",
        "Ukhrul North", "Ukhrul South", "Ukhrul East", "Ukhrul West", "Ukhrul Central"
      ]
    },
    {
      "state": "Meghalaya",
      "districts": [
        "East Garo Hills North", "East Garo Hills South", "East Garo Hills East", "East Garo Hills West", "East Garo Hills Central",
        "East Jaintia Hills North", "East Jaintia Hills South", "East Jaintia Hills East", "East Jaintia Hills West", "East Jaintia Hills Central",
        "East Khasi Hills North", "East Khasi Hills South", "East Khasi Hills East", "East Khasi Hills West", "East Khasi Hills Central",
        "North Garo Hills North", "North Garo Hills South", "North Garo Hills East", "North Garo Hills West", "North Garo Hills Central",
        "Ri Bhoi North", "Ri Bhoi South", "Ri Bhoi East", "Ri Bhoi West", "Ri Bhoi Central",
        "South Garo Hills North", "South Garo Hills South", "South Garo Hills East", "South Garo Hills West", "South Garo Hills Central",
        "South West Garo Hills North", "South West Garo Hills South", "South West Garo Hills East", "South West Garo Hills West", "South West Garo Hills Central",
        "South West Khasi Hills North", "South West Khasi Hills South", "South West Khasi Hills East", "South West Khasi Hills West", "South West Khasi Hills Central",
        "West Garo Hills North", "West Garo Hills South", "West Garo Hills East", "West Garo Hills West", "West Garo Hills Central",
        "West Jaintia Hills North", "West Jaintia Hills South", "West Jaintia Hills East", "West Jaintia Hills West", "West Jaintia Hills Central",
        "West Khasi Hills North", "West Khasi Hills South", "West Khasi Hills East", "West Khasi Hills West", "West Khasi Hills Central"
      ]
    },
    {
      "state": "Mizoram",
      "districts": [
        "Aizawl North", "Aizawl South", "Aizawl East", "Aizawl West", "Aizawl Central",
        "Champhai North", "Champhai South", "Champhai East", "Champhai West", "Champhai Central",
        "Kolasib North", "Kolasib South", "Kolasib East", "Kolasib West", "Kolasib Central",
        "Lawngtlai North", "Lawngtlai South", "Lawngtlai East", "Lawngtlai West", "Lawngtlai Central",
        "Lunglei North", "Lunglei South", "Lunglei East", "Lunglei West", "Lunglei Central",
        "Mamit North", "Mamit South", "Mamit East", "Mamit West", "Mamit Central",
        "Saiha North", "Saiha South", "Saiha East", "Saiha West", "Saiha Central",
        "Serchhip North", "Serchhip South", "Serchhip East", "Serchhip West", "Serchhip Central"
      ]
    },
    {
      "state": "Nagaland",
      "districts": [
        "Dimapur North", "Dimapur South", "Dimapur East", "Dimapur West", "Dimapur Central",
        "Kiphire North", "Kiphire South", "Kiphire East", "Kiphire West", "Kiphire Central",
        "Kohima North", "Kohima South", "Kohima East", "Kohima West", "Kohima Central",
        "Longleng North", "Longleng South", "Longleng East", "Longleng West", "Longleng Central",
        "Mokokchung North", "Mokokchung South", "Mokokchung East", "Mokokchung West", "Mokokchung Central",
        "Mon North", "Mon South", "Mon East", "Mon West", "Mon Central",
        "Peren North", "Peren South", "Peren East", "Peren West", "Peren Central",
        "Phek North", "Phek South", "Phek East", "Phek West", "Phek Central",
        "Tuensang North", "Tuensang South", "Tuensang East", "Tuensang West", "Tuensang Central",
        "Wokha North", "Wokha South", "Wokha East", "Wokha West", "Wokha Central",
        "Zunheboto North", "Zunheboto South", "Zunheboto East", "Zunheboto West", "Zunheboto Central"
      ]
    },
  {
    "state": "Odisha",
    "districts": [
      "Angul North", "Angul South", "Angul East", "Angul West", "Angul Central",
      "Balangir North", "Balangir South", "Balangir East", "Balangir West", "Balangir Central",
      "Balasore North", "Balasore South", "Balasore East", "Balasore West", "Balasore Central",
      "Bargarh North", "Bargarh South", "Bargarh East", "Bargarh West", "Bargarh Central",
      "Bhadrak North", "Bhadrak South", "Bhadrak East", "Bhadrak West", "Bhadrak Central",
      "Boudh North", "Boudh South", "Boudh East", "Boudh West", "Boudh Central",
      "Cuttack North", "Cuttack South", "Cuttack East", "Cuttack West", "Cuttack Central",
      "Deogarh North", "Deogarh South", "Deogarh East", "Deogarh West", "Deogarh Central",
      "Dhenkanal North", "Dhenkanal South", "Dhenkanal East", "Dhenkanal West", "Dhenkanal Central",
      "Gajapati North", "Gajapati South", "Gajapati East", "Gajapati West", "Gajapati Central",
      "Ganjam North", "Ganjam South", "Ganjam East", "Ganjam West", "Ganjam Central",
      "Jagatsinghpur North", "Jagatsinghpur South", "Jagatsinghpur East", "Jagatsinghpur West", "Jagatsinghpur Central",
      "Jajpur North", "Jajpur South", "Jajpur East", "Jajpur West", "Jajpur Central",
      "Jharsuguda North", "Jharsuguda South", "Jharsuguda East", "Jharsuguda West", "Jharsuguda Central",
      "Kalahandi North", "Kalahandi South", "Kalahandi East", "Kalahandi West", "Kalahandi Central",
      "Kandhamal North", "Kandhamal South", "Kandhamal East", "Kandhamal West", "Kandhamal Central",
      "Kendrapara North", "Kendrapara South", "Kendrapara East", "Kendrapara West", "Kendrapara Central",
      "Kendujhar North", "Kendujhar South", "Kendujhar East", "Kendujhar West", "Kendujhar Central",
      "Khordha North", "Khordha South", "Khordha East", "Khordha West", "Khordha Central",
      "Koraput North", "Koraput South", "Koraput East", "Koraput West", "Koraput Central",
      "Malkangiri North", "Malkangiri South", "Malkangiri East", "Malkangiri West", "Malkangiri Central",
      "Mayurbhanj North", "Mayurbhanj South", "Mayurbhanj East", "Mayurbhanj West", "Mayurbhanj Central",
      "Nabarangpur North", "Nabarangpur South", "Nabarangpur East", "Nabarangpur West", "Nabarangpur Central",
      "Nayagarh North", "Nayagarh South", "Nayagarh East", "Nayagarh West", "Nayagarh Central",
      "Nuapada North", "Nuapada South", "Nuapada East", "Nuapada West", "Nuapada Central",
      "Puri North", "Puri South", "Puri East", "Puri West", "Puri Central",
      "Rayagada North", "Rayagada South", "Rayagada East", "Rayagada West", "Rayagada Central",
      "Sambalpur North", "Sambalpur South", "Sambalpur East", "Sambalpur West", "Sambalpur Central",
      "Sonepur North", "Sonepur South", "Sonepur East", "Sonepur West", "Sonepur Central",
      "Sundargarh North", "Sundargarh South", "Sundargarh East", "Sundargarh West", "Sundargarh Central"
    ]
  },
  {
    "state": "Punjab",
    "districts": [
      "Amritsar North", "Amritsar South", "Amritsar East", "Amritsar West", "Amritsar Central",
      "Barnala North", "Barnala South", "Barnala East", "Barnala West", "Barnala Central",
      "Bathinda North", "Bathinda South", "Bathinda East", "Bathinda West", "Bathinda Central",
      "Faridkot North", "Faridkot South", "Faridkot East", "Faridkot West", "Faridkot Central",
      "Fatehgarh Sahib North", "Fatehgarh Sahib South", "Fatehgarh Sahib East", "Fatehgarh Sahib West", "Fatehgarh Sahib Central",
      "Fazilka North", "Fazilka South", "Fazilka East", "Fazilka West", "Fazilka Central",
      "Ferozepur North", "Ferozepur South", "Ferozepur East", "Ferozepur West", "Ferozepur Central",
      "Gurdaspur North", "Gurdaspur South", "Gurdaspur East", "Gurdaspur West", "Gurdaspur Central",
      "Hoshiarpur North", "Hoshiarpur South", "Hoshiarpur East", "Hoshiarpur West", "Hoshiarpur Central",
      "Jalandhar North", "Jalandhar South", "Jalandhar East", "Jalandhar West", "Jalandhar Central",
      "Kapurthala North", "Kapurthala South", "Kapurthala East", "Kapurthala West", "Kapurthala Central",
      "Ludhiana North", "Ludhiana South", "Ludhiana East", "Ludhiana West", "Ludhiana Central",
      "Mansa North", "Mansa South", "Mansa East", "Mansa West", "Mansa Central",
      "Moga North", "Moga South", "Moga East", "Moga West", "Moga Central",
      "Pathankot North", "Pathankot South", "Pathankot East", "Pathankot West", "Pathankot Central",
      "Patiala North", "Patiala South", "Patiala East", "Patiala West", "Patiala Central",
      "Rupnagar North", "Rupnagar South", "Rupnagar East", "Rupnagar West", "Rupnagar Central",
      "Sahibzada Ajit Singh Nagar North", "Sahibzada Ajit Singh Nagar South", "Sahibzada Ajit Singh Nagar East", "Sahibzada Ajit Singh Nagar West", "Sahibzada Ajit Singh Nagar Central",
      "Sangrur North", "Sangrur South", "Sangrur East", "Sangrur West", "Sangrur Central",
      "Shahid Bhagat Singh Nagar North", "Shahid Bhagat Singh Nagar South", "Shahid Bhagat Singh Nagar East", "Shahid Bhagat Singh Nagar West", "Shahid Bhagat Singh Nagar Central",
      "Sri Muktsar Sahib North", "Sri Muktsar Sahib South", "Sri Muktsar Sahib East", "Sri Muktsar Sahib West", "Sri Muktsar Sahib Central",
      "Tarn Taran North", "Tarn Taran South", "Tarn Taran East", "Tarn Taran West", "Tarn Taran Central"
    ]
  },
  {
    "state": "Rajasthan",
    "districts": [
      "Ajmer North", "Ajmer South", "Ajmer East", "Ajmer West", "Ajmer Central",
      "Alwar North", "Alwar South", "Alwar East", "Alwar West", "Alwar Central",
      "Banswara North", "Banswara South", "Banswara East", "Banswara West", "Banswara Central",
      "Baran North", "Baran South", "Baran East", "Baran West", "Baran Central",
      "Barmer North", "Barmer South", "Barmer East", "Barmer West", "Barmer Central",
      "Bharatpur North", "Bharatpur South", "Bharatpur East", "Bharatpur West", "Bharatpur Central",
      "Bhilwara North", "Bhilwara South", "Bhilwara East", "Bhilwara West", "Bhilwara Central",
      "Bikaner North", "Bikaner South", "Bikaner East", "Bikaner West", "Bikaner Central",
      "Bundi North", "Bundi South", "Bundi East", "Bundi West", "Bundi Central",
      "Chittorgarh North", "Chittorgarh South", "Chittorgarh East", "Chittorgarh West", "Chittorgarh Central",
      "Churu North", "Churu South", "Churu East", "Churu West", "Churu Central",
      "Dausa North", "Dausa South", "Dausa East", "Dausa West", "Dausa Central",
      "Dholpur North", "Dholpur South", "Dholpur East", "Dholpur West", "Dholpur Central",
      "Dungarpur North", "Dungarpur South", "Dungarpur East", "Dungarpur West", "Dungarpur Central",
      "Hanumangarh North", "Hanumangarh South", "Hanumangarh East", "Hanumangarh West", "Hanumangarh Central",
      "Jaipur North", "Jaipur South", "Jaipur East", "Jaipur West", "Jaipur Central",
      "Jaisalmer North", "Jaisalmer South", "Jaisalmer East", "Jaisalmer West", "Jaisalmer Central",
      "Jalore North", "Jalore South", "Jalore East", "Jalore West", "Jalore Central",
      "Jhalawar North", "Jhalawar South", "Jhalawar East", "Jhalawar West", "Jhalawar Central",
      "Jhunjhunu North", "Jhunjhunu South", "Jhunjhunu East", "Jhunjhunu West", "Jhunjhunu Central",
      "Jodhpur North", "Jodhpur South", "Jodhpur East", "Jodhpur West", "Jodhpur Central",
      "Karauli North", "Karauli South", "Karauli East", "Karauli West", "Karauli Central",
      "Kota North", "Kota South", "Kota East", "Kota West", "Kota Central",
      "Nagaur North", "Nagaur South", "Nagaur East", "Nagaur West", "Nagaur Central",
      "Pali North", "Pali South", "Pali East", "Pali West", "Pali Central",
      "Pratapgarh North", "Pratapgarh South", "Pratapgarh East", "Pratapgarh West", "Pratapgarh Central",
      "Rajsamand North", "Rajsamand South", "Rajsamand East", "Rajsamand West", "Rajsamand Central",
      "Sawai Madhopur North", "Sawai Madhopur South", "Sawai Madhopur East", "Sawai Madhopur West", "Sawai Madhopur Central",
      "Sikar North", "Sikar South", "Sikar East", "Sikar West", "Sikar Central",
      "Sirohi North", "Sirohi South", "Sirohi East", "Sirohi West", "Sirohi Central",
      "Sri Ganganagar North", "Sri Ganganagar South", "Sri Ganganagar East", "Sri Ganganagar West", "Sri Ganganagar Central",
      "Tonk North", "Tonk South", "Tonk East", "Tonk West", "Tonk Central",
      "Udaipur North", "Udaipur South", "Udaipur East", "Udaipur West", "Udaipur Central"
    ]
  },
  {
    "state": "Sikkim",
    "districts": [
      "East Sikkim North", "East Sikkim South", "East Sikkim East", "East Sikkim West", "East Sikkim Central",
      "North Sikkim North", "North Sikkim South", "North Sikkim East", "North Sikkim West", "North Sikkim Central",
      "South Sikkim North", "South Sikkim South", "South Sikkim East", "South Sikkim West", "South Sikkim Central",
      "West Sikkim North", "West Sikkim South", "West Sikkim East", "West Sikkim West", "West Sikkim Central"
    ]
  },
  {
    "state": "Tamil Nadu",
    "districts": [
      "Ariyalur North", "Ariyalur South", "Ariyalur East", "Ariyalur West", "Ariyalur Central",
      "Chengalpattu North", "Chengalpattu South", "Chengalpattu East", "Chengalpattu West", "Chengalpattu Central",
      "Chennai North", "Chennai South", "Chennai East", "Chennai West", "Chennai Central",
      "Coimbatore North", "Coimbatore South", "Coimbatore East", "Coimbatore West", "Coimbatore Central",
      "Cuddalore North", "Cuddalore South", "Cuddalore East", "Cuddalore West", "Cuddalore Central",
      "Dharmapuri North", "Dharmapuri South", "Dharmapuri East", "Dharmapuri West", "Dharmapuri Central",
      "Dindigul North", "Dindigul South", "Dindigul East", "Dindigul West", "Dindigul Central",
      "Erode North", "Erode South", "Erode East", "Erode West", "Erode Central",
      "Kallakurichi North", "Kallakurichi South", "Kallakurichi East", "Kallakurichi West", "Kallakurichi Central",
      "Kanchipuram North", "Kanchipuram South", "Kanchipuram East", "Kanchipuram West", "Kanchipuram Central",
      "Kanyakumari North", "Kanyakumari South", "Kanyakumari East", "Kanyakumari West", "Kanyakumari Central",
      "Karur North", "Karur South", "Karur East", "Karur West", "Karur Central",
      "Krishnagiri North", "Krishnagiri South", "Krishnagiri East", "Krishnagiri West", "Krishnagiri Central",
      "Madurai North", "Madurai South", "Madurai East", "Madurai West", "Madurai Central",
      "Nagapattinam North", "Nagapattinam South", "Nagapattinam East", "Nagapattinam West", "Nagapattinam Central",
      "Namakkal North", "Namakkal South", "Namakkal East", "Namakkal West", "Namakkal Central",
      "Nilgiris North", "Nilgiris South", "Nilgiris East", "Nilgiris West", "Nilgiris Central",
      "Perambalur North", "Perambalur South", "Perambalur East", "Perambalur West", "Perambalur Central",
      "Pudukkottai North", "Pudukkottai South", "Pudukkottai East", "Pudukkottai West", "Pudukkottai Central",
      "Ramanathapuram North", "Ramanathapuram South", "Ramanathapuram East", "Ramanathapuram West", "Ramanathapuram Central",
      "Ranipet North", "Ranipet South", "Ranipet East", "Ranipet West", "Ranipet Central",
      "Salem North", "Salem South", "Salem East", "Salem West", "Salem Central",
      "Sivaganga North", "Sivaganga South", "Sivaganga East", "Sivaganga West", "Sivaganga Central",
      "Tenkasi North", "Tenkasi South", "Tenkasi East", "Tenkasi West", "Tenkasi Central",
      "Thanjavur North", "Thanjavur South", "Thanjavur East", "Thanjavur West", "Thanjavur Central",
      "Theni North", "Theni South", "Theni East", "Theni West", "Theni Central",
      "Thoothukudi North", "Thoothukudi South", "Thoothukudi East", "Thoothukudi West", "Thoothukudi Central",
      "Tiruchirappalli North", "Tiruchirappalli South", "Tiruchirappalli East", "Tiruchirappalli West", "Tiruchirappalli Central",
      "Tirunelveli North", "Tirunelveli South", "Tirunelveli East", "Tirunelveli West", "Tirunelveli Central",
      "Tirupathur North", "Tirupathur South", "Tirupathur East", "Tirupathur West", "Tirupathur Central",
      "Tiruppur North", "Tiruppur South", "Tiruppur East", "Tiruppur West", "Tiruppur Central",
      "Tiruvallur North", "Tiruvallur South", "Tiruvallur East", "Tiruvallur West", "Tiruvallur Central",
      "Tiruvannamalai North", "Tiruvannamalai South", "Tiruvannamalai East", "Tiruvannamalai West", "Tiruvannamalai Central",
      "Tiruvarur North", "Tiruvarur South", "Tiruvarur East", "Tiruvarur West", "Tiruvarur Central",
      "Vellore North", "Vellore South", "Vellore East", "Vellore West", "Vellore Central",
      "Viluppuram North", "Viluppuram South", "Viluppuram East", "Viluppuram West", "Viluppuram Central",
      "Virudhunagar North", "Virudhunagar South", "Virudhunagar East", "Virudhunagar West", "Virudhunagar Central"
    ]
  },

    {
      "state": "Telangana",
      "districts": [
        "Adilabad",
        "Bhadradri Kothagudem",
        "Hyderabad",
        "Jagtial",
        "Jangaon",
        "Jayashankar Bhupalpally",
        "Jogulamba Gadwal",
        "Kamareddy",
        "Karimnagar",
        "Khammam",
        "Komaram Bheem",
        "Mahabubabad",
        "Mahabubnagar",
        "Mancherial",
        "Medak",
        "Medchal-Malkajgiri",
        "Nagarkurnool",
        "Nalgonda",
        "Nirmal",
        "Nizamabad",
        "Peddapalli",
        "Rajanna Sircilla",
        "Rangareddy",
        "Sangareddy",
        "Siddipet",
        "Suryapet",
        "Vikarabad",
        "Wanaparthy",
        "Warangal Rural",
        "Warangal Urban",
        "Yadadri Bhuvanagiri"
      ]
    },
    {
      "state": "Tripura",
      "districts": [
        "Dhalai",
        "Gomati",
        "Khowai",
        "North Tripura",
        "Sepahijala",
        "South Tripura",
        "Unakoti",
        "West Tripura"
      ]
    },
    {
      "state": "Uttar Pradesh",
      "districts": [
        "Agra",
        "Aligarh",
        "Allahabad",
        "Ambedkar Nagar",
        "Amethi",
        "Amroha",
        "Auraiya",
        "Azamgarh",
        "Baghpat",
        "Bahraich",
        "Ballia",
        "Balrampur",
        "Banda",
        "Barabanki",
        "Bareilly",
        "Basti",
        "Bhadohi",
        "Bijnor",
        "Budaun",
        "Bulandshahr",
        "Chandauli",
        "Chitrakoot",
        "Deoria",
        "Etah",
        "Etawah",
        "Faizabad",
        "Farrukhabad",
        "Fatehpur",
        "Firozabad",
        "Gautam Buddha Nagar",
        "Ghaziabad",
        "Ghazipur",
        "Gonda",
        "Gorakhpur",
        "Hamirpur",
        "Hapur",
        "Hardoi",
        "Hathras",
        "Jalaun",
        "Jaunpur",
        "Jhansi",
        "Kannauj",
        "Kanpur Dehat",
        "Kanpur Nagar",
        "Kasganj",
        "Kaushambi",
        "Kheri",
        "Kushinagar",
        "Lalitpur",
        "Lucknow",
        "Maharajganj",
        "Mahoba",
        "Mainpuri",
        "Mathura",
        "Mau",
        "Meerut",
        "Mirzapur",
        "Moradabad",
        "Muzaffarnagar",
        "Pilibhit",
        "Pratapgarh",
        "Raebareli",
        "Rampur",
        "Saharanpur",
        "Sambhal",
        "Sant Kabir Nagar",
        "Shahjahanpur",
        "Shamli",
        "Shravasti",
        "Siddharthnagar",
        "Sitapur",
        "Sonbhadra",
        "Sultanpur",
        "Unnao",
        "Varanasi"
      ]
    },
    {
      "state": "Uttarakhand",
      "districts": [
        "Almora",
        "Bageshwar",
        "Chamoli",
        "Champawat",
        "Dehradun",
        "Haridwar",
        "Nainital",
        "Pauri Garhwal",
        "Pithoragarh",
        "Rudraprayag",
        "Tehri Garhwal",
        "Udham Singh Nagar",
        "Uttarkashi"
      ]
    },
    {
      "state": "West Bengal",
      "districts": [
        "Alipurduar",
        "Bankura",
        "Birbhum",
        "Cooch Behar",
        "Dakshin Dinajpur",
        "Darjeeling",
        "Hooghly",
        "Howrah",
        "Jalpaiguri",
        "Jhargram",
        "Kalimpong",
        "Kolkata",
        "Malda",
        "Murshidabad",
        "Nadia",
        "North 24 Parganas",
        "Paschim Bardhaman",
        "Paschim Medinipur",
        "Purba Bardhaman",
        "Purba Medinipur",
        "Purulia",
        "South 24 Parganas",
        "Uttar Dinajpur"
      ]
    },
    {
      "state": "Andaman and Nicobar Islands",
      "districts": [
        "Nicobar",
        "North and Middle Andaman",
        "South Andaman"
      ]
    },
    {
      "state": "Chandigarh",
      "districts": ["Chandigarh"]
    },
    {
      "state": "Dadra and Nagar Haveli and Daman and Diu",
      "districts": ["Dadra and Nagar Haveli", "Daman", "Diu"]
    },
    {
      "state": "Delhi",
      "districts": [
        "Central Delhi",
        "East Delhi",
        "New Delhi",
        "North Delhi",
        "North East Delhi",
        "North West Delhi",
        "Shahdara",
        "South Delhi",
        "South East Delhi",
        "South West Delhi",
        "West Delhi"
      ]
    },
    {
      "state": "Jammu and Kashmir",
      "districts": [
        "Anantnag",
        "Bandipora",
        "Baramulla",
        "Budgam",
        "Doda",
        "Ganderbal",
        "Jammu",
        "Kathua",
        "Kishtwar",
        "Kulgam",
        "Kupwara",
        "Poonch",
        "Pulwama",
        "Rajouri",
        "Ramban",
        "Reasi",
        "Samba",
        "Shopian",
        "Srinagar",
        "Udhampur"
      ]
    },
    {
      "state": "Ladakh",
      "districts": ["Kargil", "Leh"]
    },
    {
      "state": "Lakshadweep",
      "districts": ["Lakshadweep"]
    },
    {
      "state": "Puducherry",
      "districts": ["Karaikal", "Mahe", "Puducherry", "Yanam"]
    }
  ]
}
